dash_kline_charts/DashKLineChart.py
dash_kline_charts/__init__.py
dash_kline_charts/_imports_.py
dash_kline_charts/_version.py
dash_kline_charts/dash_kline_charts.min.js
dash_kline_charts/dash_kline_charts.min.js.map
dash_kline_charts/klinecharts.min.js
dash_kline_charts/metadata.json
dash_kline_charts/package-info.json
dash_kline_charts-0.4.0.dist-info/licenses/LICENSE
dash_kline_charts-0.4.0.dist-info/METADATA
dash_kline_charts-0.4.0.dist-info/WHEEL
dash_kline_charts-0.4.0.dist-info/top_level.txt
dash_kline_charts-0.4.0.dist-info/RECORD
