Metadata-Version: 2.4
Name: dash-kline-charts
Version: 0.4.0
Summary: A Dash component for displaying financial charts using KLineChart
Home-page: https://github.com/kingzeus/dash-kline-charts
Author: Yefei Fan
Author-email: Yefei Fan <fyfcnc@gmail.com>
License-Expression: Apache-2.0
Project-URL: Homepage, https://github.com/your-username/dash-kline-charts
Project-URL: Repository, https://github.com/your-username/dash-kline-charts
Project-URL: Documentation, https://github.com/your-username/dash-kline-charts/blob/main/docs/API.md
Project-URL: Bug Tracker, https://github.com/your-username/dash-kline-charts/issues
Keywords: dash,plotly,react,kline,chart,financial,candlestick
Classifier: Development Status :: 3 - Alpha
Classifier: Framework :: Dash
Classifier: Intended Audience :: Developers
Classifier: Intended Audience :: Financial and Insurance Industry
Classifier: Operating System :: OS Independent
Classifier: Programming Language :: Python :: 3
Classifier: Programming Language :: Python :: 3.7
Classifier: Programming Language :: Python :: 3.8
Classifier: Programming Language :: Python :: 3.9
Classifier: Programming Language :: Python :: 3.10
Classifier: Programming Language :: Python :: 3.11
Classifier: Topic :: Scientific/Engineering :: Visualization
Classifier: Topic :: Office/Business :: Financial
Requires-Python: >=3.7
License-File: LICENSE
Requires-Dist: dash>=2.0.0
Requires-Dist: plotly>=5.0.0
Provides-Extra: dev
Requires-Dist: pytest>=6.0.0; extra == "dev"
Requires-Dist: pytest-cov>=2.0.0; extra == "dev"
Requires-Dist: black>=21.0.0; extra == "dev"
Requires-Dist: flake8>=3.8.0; extra == "dev"
Requires-Dist: mypy>=0.910; extra == "dev"
Dynamic: author
Dynamic: home-page
Dynamic: license-file
Dynamic: requires-python
